ptuevents/__init__.py
ptuevents/filters.py
ptuevents/filtersets.py
ptuevents/forms.py
ptuevents/graphql.py
ptuevents/models.py
ptuevents/navigation.py
ptuevents/search.py
ptuevents/tables.py
ptuevents/template_content.py
ptuevents/urls.py
ptuevents/views.py
ptuevents/api/__init__.py
ptuevents/api/serializers.py
ptuevents/api/urls.py
ptuevents/api/views.py
ptuevents/migrations/0001_initial.py
ptuevents/migrations/0002_add_sid_location.py
ptuevents/migrations/0003_alter_ptappsystem_custom_field_data_and_more.py
ptuevents/migrations/0004_rename_content_type_ptappsystemassignment_object_type_and_more.py
ptuevents/migrations/__init__.py
ptuevents/templates/ptuevents/appsystem_assignment_edit.html
ptuevents/templates/ptuevents/appsystem_panel.html
ptuevents/templates/ptuevents/ptappsystem.html
ptuevents/templates/ptuevents/ptuevent.html
ptuevents/templates/ptuevents/ptuevent_assignment_edit.html
ptuevents/templates/ptuevents/ptuevent_panel.html
ptuevents/templates/ptuevents/ptueventrelation.html
ptuevents/templates/ptuevents/ptusers.html
ptuevents/templates/ptuevents/ptusers_add.html
ptuevents/templates/ptuevents/ptworkstations.html
ptuevents/templates/ptuevents/ptworkstations_assignment_edit.html
ptuevents/templates/ptuevents/ptworkstations_panel.html
netbox_unacceptable_events-0.2.1.dist-info/LICENSE
netbox_unacceptable_events-0.2.1.dist-info/METADATA
netbox_unacceptable_events-0.2.1.dist-info/WHEEL
netbox_unacceptable_events-0.2.1.dist-info/top_level.txt
netbox_unacceptable_events-0.2.1.dist-info/RECORD
